qubicon_client/__init__.py
qubicon_client/auth.py
qubicon_client/client.py
qubicon_client/config.py
qubicon_client/utils.py
qubicon_client/functions/__init__.py
qubicon_client/functions/basic_functions.py
qubicon_client/functions/export_functions.py
qubicon_client/functions/import_functions.py
qubicon_client/functions/interactive_functions.py
qubicon_client/functions/process_functions.py
qubicon_client-1.0.0.dist-info/METADATA
qubicon_client-1.0.0.dist-info/WHEEL
qubicon_client-1.0.0.dist-info/entry_points.txt
qubicon_client-1.0.0.dist-info/top_level.txt
qubicon_client-1.0.0.dist-info/RECORD
