Metadata-Version: 2.1
Name: qubicon-client
Version: 1.0.0
Summary: CLI for interacting with the Qubicon platform
Home-page: https://git.qub-lab.io/qub-client/models-client
Author: Stephan Karas
Author-email: stephan.karas@qubicon-ag.com
Classifier: Programming Language :: Python :: 3
Classifier: Operating System :: OS Independent
Requires-Python: >=3.6
Requires-Dist: pandas ==2.2.3
Requires-Dist: rapidfuzz ==3.9.6
Requires-Dist: requests ==2.32.3
Requires-Dist: rich ==13.9.3
Requires-Dist: tabulate ==0.9.0
